[{"title":"Official BRABU Website","description":"University news and academic information.","link":"https://brabu.net/"},{"title":"Official Result","description":"Check BRABU examination results.","link":"https://brabu.net/result/"},{"title":"Official Admit Card","description":"Download examination admit cards.","link":"https://brabu.net/"},{"title":"Official Syllabus","description":"University-approved syllabus information.","link":"https://brabu.net/"},{"title":"Official Notice","description":"Latest university notices.","link":"https://brabu.net/"},{"title":"Official Examination","description":"Examination forms and schedules.","link":"https://brabu.net/"}]
